Workbook

Sheet ①先读我
B2: 申请人三分归类 · 复核工作表
B3: GECC4130 FYP · 附录A 指标8「企业专利族数」的前置工序
B4: 数据源：raw/patents_assignees.csv（2 845 个申请人 / 11 770 家族次）· 生成 2026-08-31
B6: 要做什么
B7: 只有一件事：给每个申请人填 sector（company / university / public_rd / individual / exclude）。
B8: 填完后跑 scripts/sector_export.py，它把本表导成 config/patents_assignee_sector.csv，
B9: 再跑 patents_build.py --sector company，才是指标 8 的正式口径。
B11: 好消息：规则已经把 91% 填好了
B12: 关键词规则（UNIV / INST / HOSPITAL / PTE LTD 等）已预填，confidence=high 的不用看。
B14: 预填结果 | C14: 申请人数 | D14: 家族次 | E14: 占家族次
B15: company（high） | C15: =COUNTIFS(③归类总表!$B:$B,"company",③归类总表!$C:$C,"high") -> 1972 | D15: =SUMIFS(③归类总表!$D:$D,③归类总表!$B:$B,"company",③归类总表!$C:$C,"high") -> 7849 | E15: =D15/$D$22 -> 0.668
B16: university（high） | C16: =COUNTIFS(③归类总表!$B:$B,"university",③归类总表!$C:$C,"high") -> 56 | D16: =SUMIFS(③归类总表!$D:$D,③归类总表!$B:$B,"university",③归类总表!$C:$C,"high") -> 1669 | E16: =D16/$D$22 -> 0.14204255
B17: public_rd（high） | C17: =COUNTIFS(③归类总表!$B:$B,"public_rd",③归类总表!$C:$C,"high") -> 63 | D17: =SUMIFS(③归类总表!$D:$D,③归类总表!$B:$B,"public_rd",③归类总表!$C:$C,"high") -> 1225 | E17: =D17/$D$22 -> 0.10425532
B18: individual（med） | C18: =COUNTIFS(③归类总表!$B:$B,"individual",③归类总表!$C:$C,"med") -> 687 | D18: =SUMIFS(③归类总表!$D:$D,③归类总表!$B:$B,"individual",③归类总表!$C:$C,"med") -> 920 | E18: =D18/$D$22 -> 0.078297872
B19: public_rd（med） | C19: =COUNTIFS(③归类总表!$B:$B,"public_rd",③归类总表!$C:$C,"med") -> 31 | D19: =SUMIFS(③归类总表!$D:$D,③归类总表!$B:$B,"public_rd",③归类总表!$C:$C,"med") -> 68 | E19: =D19/$D$22 -> 0.005787234
B20: company（med） | C20: =COUNTIFS(③归类总表!$B:$B,"company",③归类总表!$C:$C,"med") -> 17 | D20: =SUMIFS(③归类总表!$D:$D,③归类总表!$B:$B,"company",③归类总表!$C:$C,"med") -> 19 | E20: =D20/$D$22 -> 0.0016170213
B21: 未分类（low） | C21: =COUNTIFS(③归类总表!$B:$B,"",③归类总表!$C:$C,"low") -> 0 | D21: =SUMIFS(③归类总表!$D:$D,③归类总表!$B:$B,"",③归类总表!$C:$C,"low") -> 0 | E21: =D21/$D$22 -> 0
B22: 合计 | C22: =SUM(C15:C21) -> 2826 | D22: =SUM(D15:D21) -> 11750 | E22: =D22/$D$22 -> 1
B24: 两个要拍板的口径问题
B25: 决策 1 | C25: 687 个「individual」怎么算？
C26: 发明人自持专利，921 家族次占 7.8%。指标 8 叫「企业专利族数」——自然人自持
C27: 通常不算企业。建议整批 exclude，但这是一次性决定，不用逐行看。
B29: 决策 2 | C29: InnoHK 中心算 public_rd 还是 university？
C30: 表②里有一批 CENTRE FOR xxx LTD（NOVOSTICS / CVVT / CIMDA / COCHE / 眼视觉…），
C31: 都是 InnoHK 中心：法律上是公司，实际是政府资助、挂靠大学的研发中心。
C32: 顺带：这批名单正好能回答挂了很久的「InnoHK 25 还是 30」那个差额问题。
B34: 逐行要看的只有 67 行
B35: 全在表②「②需人工确认」，占家族次 0.9%。黄底格子＝请填/请确认。
B36: 表③是全量 2 845 行（含已填好的），表④是名称变体，供参考。
B38: 顺手记一笔：源数据本身有脏名
B39: ASTRI 在 assignee_harmonized 里有 7 种拼法，含 “APPLIES SCIENCE”“TECHNOLOY” 这类错字；
B40: “City Iniversity of Hong Kong” 是 University 的错字；
B41: “METHOD FOR DIAGNOSIS AND PROGNOSIS OF CHRONIC HEART FAILURE…” 是把专利标题写进了申请人字段。
B42: 结论：BigQuery 的 assignee_harmonized 并没有真正 harmonized，报「top 申请人」时要先合并变体（见表④）。

Sheet ②需人工确认
A1: 申请人 assignee | B1: sector（请确认/填写） | C1: 规则给的置信度 | D1: 家族次 | E1: 城市 | F1: 规则依据 / 备注
A2: HONG KONG CENTRE FOR CEREBRO CARDIOVASCULAR HEALTH ENGINEERING LTD | B2: public_rd | C2: med | D2: 7 | E2: hk | F2: 含 INST/AGENCY/HOSPITAL/COUNCIL/CENTRE FOR 等公营词（同时带企业后缀，请确认）
A3: CENTRE FOR INTELLIGENT MULTIDIMENSIONAL DATA ANALYSIS LTD | B3: public_rd | C3: med | D3: 6 | E3: hk | F3: 含 INST/AGENCY/HOSPITAL/COUNCIL/CENTRE FOR 等公营词（同时带企业后缀，请确认）
A4: CENTRE FOR VIROLOGY VACCINOLOGY AND THERAPEUTICS LTD | B4: public_rd | C4: med | D4: 6 | E4: hk | F4: 含 INST/AGENCY/HOSPITAL/COUNCIL/CENTRE FOR 等公营词（同时带企业后缀，请确认）
A5: HONG KONG RES INST TEXTILES & APPAREL LTD | B5: public_rd | C5: med | D5: 6 | E5: hk | F5: 含 INST/AGENCY/HOSPITAL/COUNCIL/CENTRE FOR 等公营词（同时带企业后缀，请确认）
A6: CENTRE FOR EYE AND VISION RES LIMITED | B6: public_rd | C6: med | D6: 4 | E6: hk | F6: 含 INST/AGENCY/HOSPITAL/COUNCIL/CENTRE FOR 等公营词（同时带企业后缀，请确认）
A7: AON SINGAPORE CENTRE FOR INNOVATION STRATEGY AND MAN PTE LTD | B7: public_rd | C7: med | D7: 4 | E7: sg | F7: 含 INST/AGENCY/HOSPITAL/COUNCIL/CENTRE FOR 等公营词（同时带企业后缀，请确认）
A8: HONG KONG R&D CENTRE FOR LOGISTICS AND SUPPLY CHAIN MANAGEMENT ENABLING TECH LIMITED | B8: public_rd | C8: med | D8: 3 | E8: hk | F8: 含 INST/AGENCY/HOSPITAL/COUNCIL/CENTRE FOR 等公营词（同时带企业后缀，请确认）
A9: DSO NAT LAB | B9: public_rd | C9: med | D9: 3 | E9: sg | F9: 无法定后缀，但含机构性词汇（TECH/LABS/ASIA/IP 等）
A10: CENTRE FOR IMMUNOLOGY & INFECTION LTD | B10: public_rd | C10: med | D10: 2 | E10: hk | F10: 含 INST/AGENCY/HOSPITAL/COUNCIL/CENTRE FOR 等公营词（同时带企业后缀，请确认）
A11: CENTRE FOR TRANSLATIONAL STEM CELL BIOLOGY LTD | B11: public_rd | C11: med | D11: 2 | E11: hk | F11: 含 INST/AGENCY/HOSPITAL/COUNCIL/CENTRE FOR 等公营词（同时带企业后缀，请确认）
A12: EC COUNCIL INTERNATIONAL LTD | B12: company | C12: med | D12: 2 | E12: hk | F12: 含 INST/AGENCY/HOSPITAL/COUNCIL/CENTRE FOR 等公营词（同时带企业后缀，请确认）
A13: HONG KONG CENTER FOR NEURODEGENERATIVE DISEASES LTD | B13: public_rd | C13: med | D13: 2 | E13: hk | F13: 含 INST/AGENCY/HOSPITAL/COUNCIL/CENTRE FOR 等公营词（同时带企业后缀，请确认）
... A68: VOSSELER HANS-GÜNTER | B68: individual | C68: low | D68: 1 | E68: sg | F68: ⚠️ 规则判不了，需人工

Sheet ③归类总表
A1: 申请人 assignee | B1: sector | C1: confidence | D1: 家族次 | E1: 累计占比 | F1: 城市 | G1: 规则依据
A2: ALIBABA GROUP SERVICES LTD | B2: company | C2: high | D2: 1052 | E2: =SUM($D$2:D2)/SUM($D$2:$D$2846) -> 0.089379779 | F2: hk | G2: 含企业法定后缀 LTD/PTE/INC/CORP
A3: AGENCY SCIENCE TECH & RES | B3: public_rd | C3: high | D3: 740 | E3: =SUM($D$2:D3)/SUM($D$2:$D$2846) -> 0.15225149 | F3: sg | G3: 已知实体：新加坡 A*STAR
A4: NAT UNIV SINGAPORE | B4: university | C4: high | D4: 598 | E4: =SUM($D$2:D4)/SUM($D$2:$D$2846) -> 0.20305862 | F4: sg | G4: 名称含 UNIV/POLYTECHNIC/COLLEGE
A5: LENOVO SINGAPORE PTE LTD | B5: company | C5: high | D5: 459 | E5: =SUM($D$2:D5)/SUM($D$2:$D$2846) -> 0.24205607 | F5: sg | G5: 含企业法定后缀 LTD/PTE/INC/CORP
A6: UNIV NANYANG TECH | B6: university | C6: high | D6: 391 | E6: =SUM($D$2:D6)/SUM($D$2:$D$2846) -> 0.27527613 | F6: sg | G6: 名称含 UNIV/POLYTECHNIC/COLLEGE
A7: SMITH & NEPHEW ASIA PACIFIC PTE LTD | B7: company | C7: high | D7: 311 | E7: =SUM($D$2:D7)/SUM($D$2:$D$2846) -> 0.30169924 | F7: sg | G7: 含企业法定后缀 LTD/PTE/INC/CORP
A8: UNIV CITY HONG KONG | B8: university | C8: high | D8: 184 | E8: =SUM($D$2:D8)/SUM($D$2:$D$2846) -> 0.3173322 | F8: hk | G8: 名称含 UNIV/POLYTECHNIC/COLLEGE
A9: SENSETIME INT PTE LTD | B9: company | C9: high | D9: 180 | E9: =SUM($D$2:D9)/SUM($D$2:$D$2846) -> 0.33262532 | F9: sg | G9: 含企业法定后缀 LTD/PTE/INC/CORP
A10: SINGAPORE HEALTH SERV PTE LTD | B10: public_rd | C10: high | D10: 173 | E10: =SUM($D$2:D10)/SUM($D$2:$D$2846) -> 0.3473237 | F10: sg | G10: 已知实体：SingHealth 公立医疗集团
A11: MASTERCARD ASIA PACIFIC PTE LTD | B11: company | C11: high | D11: 147 | E11: =SUM($D$2:D11)/SUM($D$2:$D$2846) -> 0.35981308 | F11: sg | G11: 含企业法定后缀 LTD/PTE/INC/CORP
A12: LEMON INC | B12: company | C12: high | D12: 129 | E12: =SUM($D$2:D12)/SUM($D$2:$D$2846) -> 0.37077315 | F12: sg | G12: 含企业法定后缀 LTD/PTE/INC/CORP
A13: LEICA INSTR SINGAPORE PTE LTD | B13: company | C13: high | D13: 112 | E13: =SUM($D$2:D13)/SUM($D$2:$D$2846) -> 0.38028887 | F13: sg | G13: 含企业法定后缀 LTD/PTE/INC/CORP
... A2846: comGateway (S) Pte Ltd | B2846: company | C2846: high | D2846: 1 | E2846: =SUM($D$2:D2846)/SUM($D$2:$D$2846) -> 1 | F2846: sg | G2846: 含企业法定后缀 LTD/PTE/INC/CORP

Sheet ④名称变体
A1: 归一化名 (仅供分组) | B1: 原始申请人名 | C1: 家族次 | D1: 预填 sector
A2: LENOVO SINGAPORE | B2: 3 种拼法 | C2: 461
B3: LENOVO SINGAPORE PTE LTD | C3: 459 | D3: company
B4: LENOVO ( SINGAPORE) PTE LTD | C4: 1 | D4: company
B5: LENOVO SINGAPORE LTD | C5: 1 | D5: company
A6: SMITH AND NEPHEW ASIA PACIFIC | B6: 2 种拼法 | C6: 312
B7: SMITH & NEPHEW ASIA PACIFIC PTE LTD | C7: 311 | D7: company
B8: SMITH & NEPHEW ASIA PACIFIC LTD | C8: 1 | D8: company
A9: LEICA INSTR SINGAPORE | B9: 2 种拼法 | C9: 126
B10: LEICA INSTR SINGAPORE PTE LTD | C10: 112 | D10: company
B11: LEICA INSTR (SINGAPORE) PTE LTD | C11: 14 | D11: company
A12: NAT UNIV HOSPITAL SINGAPORE | B12: 2 种拼法 | C12: 66
B13: NAT UNIV HOSPITAL SINGAPORE PTE LTD | C13: 59 | D13: public_rd
B14: NAT UNIV HOSPITAL (SINGAPORE) PTE LTD | C14: 7 | D14: public_rd
A15: GRABTAXI | B15: 2 种拼法 | C15: 65
B16: GRABTAXI HOLDINGS PTE LTD | C16: 64 | D16: company
B17: GRABTAXI HOLDING PTE LTD | C17: 1 | D17: company
A18: WAVE LIFE SCIENCES | B18: 2 种拼法 | C18: 52
B19: WAVE LIFE SCIENCES LTD | C19: 50 | D19: company
B20: WAVE LIFE SCIENCES PTE LTD | C20: 2 | D20: company
A21: SMITH AND NEPHEW | B21: 2 种拼法 | C21: 49
B22: SMITH & NEPHEW PTE LTD | C22: 48 | D22: company
B23: SMITH&NEPHEW PTE LTD | C23: 1 | D23: company
A24: HILL ROM SERVICES | B24: 2 种拼法 | C24: 40
B25: HILL ROM SERVICES PTE LTD | C25: 35 | D25: company
B26: HILL-ROM SERVICES PTE LTD | C26: 5 | D26: company
A27: HCP HEALTHCARE ASIA | B27: 2 种拼法 | C27: 33
B28: HCP HEALTHCARE ASIA PTE LTD | C28: 31 | D28: company
B29: HCP HEALTHCARE ASIA PTE | C29: 2 | D29: company
A30: TAN TOCK SENG HOSPITAL | B30: 2 种拼法 | C30: 33
B31: TAN TOCK SENG HOSPITAL PTE LTD | C31: 29 | D31: public_rd
B32: TAN TOCK SENG HOSPITAL | C32: 4 | D32: public_rd
A33: AON GLOBAL OPERATIONS SINGAPORE | B33: 4 种拼法 | C33: 33
B34: AON GLOBAL OPERATIONS LTD SINGAPORE BRANCH | C34: 14 | D34: company
B35: AON GLOBAL OPERATIONS SE SINGAPORE BRANCH | C35: 10 | D35: company
B36: AON GLOBAL OPERATIONS PLC SINGAPORE BRANCH | C36: 7 | D36: company
B37: Aon Global Operations Ltd (Singapore Branch) | C37: 2 | D37: company
A38: HUMMINGBIRD BIOSCIENCE | B38: 3 种拼法 | C38: 30
B39: HUMMINGBIRD BIOSCIENCE PTE LTD | C39: 15 | D39: company
B40: HUMMINGBIRD BIOSCIENCE HOLDINGS PTE LTD | C40: 10 | D40: company
B41: HUMMINGBIRD BIOSCIENCE HOLDINGS LTD | C41: 5 | D41: company
A42: TEMASEK LIFE SCIENCES LABORATORY | B42: 2 种拼法 | C42: 28
B43: TEMASEK LIFE SCIENCES LABORATORY LTD | C43: 26 | D43: company
B44: TEMASEK LIFE SCIENCES LABORATORY | C44: 2 | D44: company
A45: PUZHEN LIFE | B45: 3 种拼法 | C45: 28
B46: PUZHEN LIFE CO LTD | C46: 23 | D46: company
B47: PUZHEN LIFE CO LIMITED | C47: 3 | D47: company
B48: PUZHEN LIFE CO INC | C48: 2 | D48: company
A49: RAZER ASIA PACIFIC | B49: 2 种拼法 | C49: 25
B50: RAZER ASIA PACIFIC PTE LTD | C50: 16 | D50: company
B51: RAZER (ASIA-PACIFIC) PTE LTD | C51: 9 | D51: company
A52: AGENCY FOR SCIENCE TECH AND RESEARCH ASTARSTAR | B52: 3 种拼法 | C52: 21
B53: AGENCY FOR SCIENCE TECH AND RESEARCH ASTARSTAR | C53: 19 | D53: public_rd
B54: AGENCY FOR SCIENCE TECH AND RESEARCH ASTARSTAR] | C54: 1 | D54: public_rd
B55: AGENCY FOR SCIENCE TECH AND RESEARCH “ASTARSTAR” | C55: 1 | D55: public_rd
A56: MOFFETT INTERNATIONAL | B56: 2 种拼法 | C56: 21
B57: MOFFETT INTERNATIONAL CO LIMITED | C57: 11 | D57: company
B58: MOFFETT INTERNATIONAL CO LTD | C58: 10 | D58: company
A59: TESSA THERAPEUTICS | B59: 2 种拼法 | C59: 20
B60: TESSA THERAPEUTICS LTD | C60: 12 | D60: company
B61: TESSA THERAPEUTICS PTE LTD | C61: 8 | D61: company
A62: ANTS TECH HK | B62: 3 种拼法 | C62: 19
B63: ANTS TECH HK LIMITED | C63: 15 | D63: company
B64: ANTS TECH (HK) LTD | C64: 3 | D64: company
B65: ANTS TECH (HK) LIMITED | C65: 1 | D65: company
A66: DELTA ELECTRONICS INT L SINGAPORE | B66: 2 种拼法 | C66: 19
B67: DELTA ELECTRONICS INT’L SINGAPORE PTE LTD | C67: 15 | D67: company
B68: Delta Electronics Int'l (Singapore) Pte Ltd | C68: 4 | D68: company
A69: THUNDER POWER NEW ENERGY VEHICLE DEVELOPMENT | B69: 2 种拼法 | C69: 17
B70: THUNDER POWER NEW ENERGY VEHICLE DEVELOPMENT CO LTD | C70: 16 | D70: company
B71: THUNDER POWER NEW ENERGY VEHICLE DEVELOPMENT LTD | C71: 1 | D71: company
A72: SUNIA | B72: 2 种拼法 | C72: 15
B73: SUNIA PTE LTD | C73: 14 | D73: company
B74: SUNIA | C74: 1
A75: LIFE TECH | B75: 3 种拼法 | C75: 15
B76: LIFE TECH HOLDINGS PTE LIMITED | C76: 8 | D76: company
B77: LIFE TECH HOLDINGS PTE LTD | C77: 6 | D77: company
B78: LIFE TECH HOLDING PTE LTD | C78: 1 | D78: company
A79: EINNOVATIONS | B79: 2 种拼法 | C79: 13
B80: EINNOVATIONS HOLDINGS PTE LTD | C80: 12 | D80: company
B81: EINNOVATIONS HOLDING PTE LTD | C81: 1 | D81: company
A82: ACT GENOMICS | B82: 2 种拼法 | C82: 11
B83: ACT GENOMICS IP CO LTD | C83: 6 | D83: company
B84: ACT GENOMICS IP LTD | C84: 5 | D84: company
A85: OSIM INT | B85: 2 种拼法 | C85: 10
B86: OSIM INT PTE LTD | C86: 7 | D86: company
B87: OSIM INT LTD | C87: 3 | D87: company
A88: CENTRE FOR NOVOSTICS | B88: 2 种拼法 | C88: 10
B89: CENTRE FOR NOVOSTICS | C89: 6 | D89: public_rd
B90: CENTRE FOR NOVOSTICS LTD | C90: 4 | D90: public_rd
A91: PERFECT VISION TECH HK | B91: 2 种拼法 | C91: 10
B92: PERFECT VISION TECH HK LTD | C92: 6 | D92: company
B93: PERFECT VISION TECH (HK) LTD | C93: 4 | D93: company
A94: ACCRO BIOSCIENCE HK | B94: 2 种拼法 | C94: 9
B95: ACCRO BIOSCIENCE HK LTD | C95: 8 | D95: company
B96: ACCRO BIOSCIENCE HK | C96: 1 | D96: company
A97: TENACIA BIOTECHNOLOGY HONG KONG | B97: 2 种拼法 | C97: 8
B98: TENACIA BIOTECHNOLOGY HONG KONG CO LTD | C98: 7 | D98: company
B99: TENACIA BIOTECHNOLOGY HONG KONG CO LIMITED | C99: 1 | D99: company
A100: INNOVENT BIOLOGICS SINGAPORE | B100: 2 种拼法 | C100: 8
...
